filecoin_lotus/__init__.py
filecoin_lotus/chain.py
filecoin_lotus/encoding.py
filecoin_lotus/filecoin.py
filecoin_lotus/mpool.py
filecoin_lotus/providers.py
filecoin_lotus/rpc_abi.py
filecoin_lotus/state.py
filecoin_lotus/types_check.py
filecoin_lotus/types_fil.py
filecoin_lotus/wallet.py
filecoin_lotus-1.0.1.dist-info/LICENSE
filecoin_lotus-1.0.1.dist-info/METADATA
filecoin_lotus-1.0.1.dist-info/WHEEL
filecoin_lotus-1.0.1.dist-info/top_level.txt
filecoin_lotus-1.0.1.dist-info/RECORD
